LICENSE.md
MANIFEST.in
README.md
setup.cfg
setup.py
unvcf/__init__.py
unvcf/_cmd.py
unvcf/testit.py
unvcf.egg-info/PKG-INFO
unvcf.egg-info/SOURCES.txt
unvcf.egg-info/dependency_links.txt
unvcf.egg-info/entry_points.txt
unvcf.egg-info/not-zip-safe
unvcf.egg-info/requires.txt
unvcf.egg-info/top_level.txt
unvcf/test/__init__.py
unvcf/test/test_unvcf.py
unvcf/test/data/CEU.exon.2010_03.genotypes.vcf.bz2
unvcf/test/data/__init__.py
unvcf/test/data/aa.vcf
unvcf/test/data/ad-bias.vcf
unvcf/test/data/af-dist.vcf
unvcf/test/data/annotate.vcf
unvcf/test/data/annotate10.vcf
unvcf/test/data/annotate2.vcf
unvcf/test/data/annotate3.vcf
unvcf/test/data/annotate4.vcf
unvcf/test/data/annotate9.vcf
unvcf/test/data/annots.vcf
unvcf/test/data/annots2.vcf
unvcf/test/data/annots4.vcf
unvcf/test/data/annots9.vcf
unvcf/test/data/check.vcf
unvcf/test/data/concat.1.a.vcf
unvcf/test/data/concat.1.b.vcf
unvcf/test/data/concat.2.a.vcf
unvcf/test/data/concat.2.b.vcf
unvcf/test/data/concat.3.0.vcf
unvcf/test/data/concat.3.a.vcf
unvcf/test/data/concat.3.b.vcf
unvcf/test/data/concat.3.c.vcf
unvcf/test/data/concat.3.d.vcf
unvcf/test/data/concat.3.e.vcf
unvcf/test/data/concat.3.f.vcf
unvcf/test/data/consensus.vcf
unvcf/test/data/consensus2.vcf
unvcf/test/data/convert.23andme.vcf
unvcf/test/data/convert.gt.vcf
unvcf/test/data/convert.gvcf.vcf
unvcf/test/data/convert.vcf
unvcf/test/data/csq.vcf
unvcf/test/data/empty.vcf
unvcf/test/data/ex2.vcf
unvcf/test/data/fill-tags-hemi.vcf
unvcf/test/data/filter-missing-floats.vcf
unvcf/test/data/filter.1.vcf
unvcf/test/data/filter.2.vcf
unvcf/test/data/filter.3.vcf
unvcf/test/data/filter.4.vcf
unvcf/test/data/fixploidy.vcf
unvcf/test/data/fixref.2a.vcf
unvcf/test/data/fixref.2b.vcf
unvcf/test/data/fixref.vcf
unvcf/test/data/gvcf.merge.1.vcf
unvcf/test/data/gvcf.merge.2.vcf
unvcf/test/data/gvcf.merge.3.vcf
unvcf/test/data/idx.vcf
unvcf/test/data/isec.a.vcf
unvcf/test/data/isec.b.vcf
unvcf/test/data/large_chrom_csi_limit.vcf
unvcf/test/data/many.alleles.vcf
unvcf/test/data/mendelian.vcf
unvcf/test/data/merge.2.a.vcf
unvcf/test/data/merge.2.b.vcf
unvcf/test/data/merge.3.a.vcf
unvcf/test/data/merge.3.b.vcf
unvcf/test/data/merge.4.a.vcf
unvcf/test/data/merge.4.b.vcf
