Metadata-Version: 1.1
Name: unvcf
Version: 0.1.2
Summary: Split VCF file into intelligible tab-delimited files
Home-page: https://github.com/horta/unvcf
Author: Danilo Horta
Author-email: horta@ebi.ac.uk
License: MIT
Download-URL: https://github.com/horta/unvcf
Keywords: vcf file,genotype,variant call,converter
Platform: OS Independent
Platform: Windows
Platform: MacOS
Platform: POSIX
Platform: POSIX :: Linux
Classifier: Development Status :: 4 - Beta
Classifier: Environment :: Console
Classifier: Intended Audience :: Developers
Classifier: License :: OSI Approved :: MIT License
Classifier: Operating System :: OS Independent
Classifier: Programming Language :: Python
